st_row_buttons/__init__.py
st_row_buttons/frontend/build/asset-manifest.json
st_row_buttons/frontend/build/bootstrap.min.css
st_row_buttons/frontend/build/index.html
st_row_buttons/frontend/build/precache-manifest.3f44a68895c4fb1143362a1cc304dfc8.js
st_row_buttons/frontend/build/service-worker.js
st_row_buttons/frontend/build/static/css/main.783992f3.chunk.css
st_row_buttons/frontend/build/static/css/main.783992f3.chunk.css.map
st_row_buttons/frontend/build/static/js/2.efa84012.chunk.js
st_row_buttons/frontend/build/static/js/2.efa84012.chunk.js.LICENSE.txt
st_row_buttons/frontend/build/static/js/2.efa84012.chunk.js.map
st_row_buttons/frontend/build/static/js/main.ea20abc8.chunk.js
st_row_buttons/frontend/build/static/js/main.ea20abc8.chunk.js.map
st_row_buttons/frontend/build/static/js/runtime-main.12e05911.js
st_row_buttons/frontend/build/static/js/runtime-main.12e05911.js.map
st_row_buttons-0.0.4.dist-info/LICENSE
st_row_buttons-0.0.4.dist-info/METADATA
st_row_buttons-0.0.4.dist-info/WHEEL
st_row_buttons-0.0.4.dist-info/top_level.txt
st_row_buttons-0.0.4.dist-info/RECORD
