Metadata-Version: 2.1
Name: st-row-buttons
Version: 0.0.4
Summary: Streamlit Button Selection Component
Home-page: https://github.com/twelvefootball/st-btn-select-custom
Author: kubix
License: MIT
Platform: UNKNOWN
Requires-Python: >=3.6
Requires-Dist: streamlit (>=0.63)
